json2orm/__init__.py
json2orm/db.py
json2orm/model.py
json2orm-0.1.0.dist-info/licenses/LICENSE
json2orm-0.1.0.dist-info/METADATA
json2orm-0.1.0.dist-info/WHEEL
json2orm-0.1.0.dist-info/top_level.txt
json2orm-0.1.0.dist-info/RECORD
