Metadata-Version: 2.4
Name: json2orm
Version: 0.1.0
Summary: A simple JSON-based ORM for Python
Home-page: https://github.com/OroTeam/json2orm/
Author: Sina Firoozan(ReFrameWeb)
Author-email: sinafiroozan@gmail.com
License: MIT
Requires-Python: >=3.7
License-File: LICENSE
Dynamic: author
Dynamic: author-email
Dynamic: description
Dynamic: description-content-type
Dynamic: home-page
Dynamic: license
Dynamic: license-file
Dynamic: requires-python
Dynamic: summary
